README.rst
mipy.py
setup.py
mipy.egg-info/PKG-INFO
mipy.egg-info/SOURCES.txt
mipy.egg-info/dependency_links.txt
mipy.egg-info/entry_points.txt
mipy.egg-info/requires.txt
mipy.egg-info/top_level.txt