Metadata-Version: 1.0
Name: mipy
Version: 0.0.1
Summary: Copy files to Micropython
Home-page: https://github.com/bcb/mipy
Author: Beau Barker
Author-email: beauinmelbourne@gmail.com
License: MIT
Platform: UNKNOWN
